pytest_draw/__init__.py
pytest_draw/plugin.py
pytest_draw-0.1.dist-info/METADATA
pytest_draw-0.1.dist-info/WHEEL
pytest_draw-0.1.dist-info/entry_points.txt
pytest_draw-0.1.dist-info/top_level.txt
pytest_draw-0.1.dist-info/RECORD
